{
  "dataset": "Test_Time_Learning",
  "instance_idx": 4,
  "results": {
    "R1": [
      {
        "question": "What is the population of Venezuela ?",
        "answer": "4",
        "ground_truth": [
          "4"
        ],
        "steps": 1,
        "tokens": 1516
      },
      {
        "question": "What does target heart rate mean ?",
        "answer": "2",
        "ground_truth": [
          "3"
        ],
        "steps": 1,
        "tokens": 2057
      },
      {
        "question": "What currency does Luxembourg use ?",
        "answer": "1",
        "ground_truth": [
          "1"
        ],
        "steps": 1,
        "tokens": 3011
      },
      {
        "question": "How long did Rip Van Winkle sleep ?",
        "answer": "4",
        "ground_truth": [
          "4"
        ],
        "steps": 1,
        "tokens": 1571
      },
      {
        "question": "Material called linen is made from what plant ?",
        "answer": "1",
        "ground_truth": [
          "1"
        ],
        "steps": 1,
        "tokens": 2999
      },
      {
        "question": "What is phenylalanine ?",
        "answer": "3",
        "ground_truth": [
          "3"
        ],
        "steps": 1,
        "tokens": 1823
      },
      {
        "question": "What is a group of turkeys called ?",
        "answer": "1",
        "ground_truth": [
          "1"
        ],
        "steps": 1,
        "tokens": 1956
      },
      {
        "question": "What are enzymes ?",
        "answer": "3",
        "ground_truth": [
          "3"
        ],
        "steps": 1,
        "tokens": 1422
      },
      {
        "question": "Why is the sun yellow ?",
        "answer": "3",
        "ground_truth": [
          "3"
        ],
        "steps": 1,
        "tokens": 2807
      },
      {
        "question": "What state is the geographic center of the lower 48 states ?",
        "answer": "5",
        "ground_truth": [
          "5"
        ],
        "steps": 1,
        "tokens": 2751
      },
      {
        "question": "What is foot and mouth disease ?",
        "answer": "3",
        "ground_truth": [
          "1"
        ],
        "steps": 1,
        "tokens": 2586
      },
      {
        "question": "What is sonar ?",
        "answer": "2",
        "ground_truth": [
          "3"
        ],
        "steps": 1,
        "tokens": 1406
      },
      {
        "question": "When was Thomas Jefferson born ?",
        "answer": "4",
        "ground_truth": [
          "4"
        ],
        "steps": 1,
        "tokens": 1395
      },
      {
        "question": "What is the Ohio state bird ?",
        "answer": "1",
        "ground_truth": [
          "1"
        ],
        "steps": 1,
        "tokens": 1532
      },
      {
        "question": "What are the colors of the German flag ?",
        "answer": "1",
        "ground_truth": [
          "1"
        ],
        "steps": 1,
        "tokens": 1608
      },
      {
        "question": "Who won Ms. American in 1989 ?",
        "answer": "0",
        "ground_truth": [
          "0"
        ],
        "steps": 1,
        "tokens": 3101
      },
      {
        "question": "Where on the body is a mortarboard worn ?",
        "answer": "5",
        "ground_truth": [
          "5"
        ],
        "steps": 1,
        "tokens": 2554
      },
      {
        "question": "What is the width of a football field ?",
        "answer": "4",
        "ground_truth": [
          "4"
        ],
        "steps": 1,
        "tokens": 2789
      },
      {
        "question": "Who is the Prime Minister of Canada ?",
        "answer": "0",
        "ground_truth": [
          "0"
        ],
        "steps": 1,
        "tokens": 2618
      },
      {
        "question": "What is the conversion rate between dollars and pounds ?",
        "answer": "4",
        "ground_truth": [
          "4"
        ],
        "steps": 1,
        "tokens": 1346
      },
      {
        "question": "What is fibromyalgia ?",
        "answer": "3",
        "ground_truth": [
          "3"
        ],
        "steps": 1,
        "tokens": 3176
      },
      {
        "question": "What are the spots on dominoes called ?",
        "answer": "1",
        "ground_truth": [
          "1"
        ],
        "steps": 1,
        "tokens": 3028
      },
      {
        "question": "What city is also known as `` The Gateway to the West '' ?",
        "answer": "上下文信息不足，无法回答该问题。",
        "ground_truth": [
          "5"
        ],
        "steps": 1,
        "tokens": 1558
      },
      {
        "question": "Who discovered x-rays ?",
        "answer": "0",
        "ground_truth": [
          "0"
        ],
        "steps": 1,
        "tokens": 2510
      },
      {
        "question": "How much does water weigh ?",
        "answer": "4",
        "ground_truth": [
          "4"
        ],
        "steps": 1,
        "tokens": 2263
      },
      {
        "question": "Mercury , what year was it discovered ?",
        "answer": "4",
        "ground_truth": [
          "4"
        ],
        "steps": 1,
        "tokens": 1824
      },
      {
        "question": "Where do apple snails live ?",
        "answer": "5",
        "ground_truth": [
          "5"
        ],
        "steps": 1,
        "tokens": 3050
      },
      {
        "question": "What is the rainiest place on Earth ?",
        "answer": "5",
        "ground_truth": [
          "5"
        ],
        "steps": 1,
        "tokens": 2641
      },
      {
        "question": "Who invented the hula hoop ?",
        "answer": "0",
        "ground_truth": [
          "0"
        ],
        "steps": 1,
        "tokens": 1351
      },
      {
        "question": "What is the longest suspension bridge in the U.S. ?",
        "answer": "5",
        "ground_truth": [
          "5"
        ],
        "steps": 1,
        "tokens": 2884
      },
      {
        "question": "What is plastic made of ?",
        "answer": "1",
        "ground_truth": [
          "1"
        ],
        "steps": 1,
        "tokens": 2923
      },
      {
        "question": "How far is it from Denver to Aspen ?",
        "answer": "4",
        "ground_truth": [
          "4"
        ],
        "steps": 1,
        "tokens": 2527
      },
      {
        "question": "What is the criterion for being legally blind ?",
        "answer": "3",
        "ground_truth": [
          "1"
        ],
        "steps": 1,
        "tokens": 3329
      },
      {
        "question": "Who invented the instant Polaroid camera ?",
        "answer": "0",
        "ground_truth": [
          "0"
        ],
        "steps": 1,
        "tokens": 1361
      },
      {
        "question": "What is the distance in miles from the earth to the sun ?",
        "answer": "4",
        "ground_truth": [
          "4"
        ],
        "steps": 1,
        "tokens": 2348
      },
      {
        "question": "In which state would you find the Catskill Mountains ?",
        "answer": "5",
        "ground_truth": [
          "5"
        ],
        "steps": 1,
        "tokens": 2100
      },
      {
        "question": "What is a prism ?",
        "answer": "3",
        "ground_truth": [
          "3"
        ],
        "steps": 1,
        "tokens": 3749
      },
      {
        "question": "How fast is sound ?",
        "answer": "4",
        "ground_truth": [
          "4"
        ],
        "steps": 1,
        "tokens": 2727
      },
      {
        "question": "What does cc in engines mean ?",
        "answer": "2",
        "ground_truth": [
          "3"
        ],
        "steps": 1,
        "tokens": 2314
      },
      {
        "question": "What is an ulcer ?",
        "answer": "3",
        "ground_truth": [
          "3"
        ],
        "steps": 1,
        "tokens": 1963
      },
      {
        "question": "What is compounded interest ?",
        "answer": "3",
        "ground_truth": [
          "3"
        ],
        "steps": 1,
        "tokens": 2719
      },
      {
        "question": "What does CPR stand for ?",
        "answer": "2",
        "ground_truth": [
          "2"
        ],
        "steps": 1,
        "tokens": 1583
      },
      {
        "question": "What is hybridization ?",
        "answer": "3",
        "ground_truth": [
          "3"
        ],
        "steps": 1,
        "tokens": 3129
      },
      {
        "question": "How fast is alcohol absorbed ?",
        "answer": "4",
        "ground_truth": [
          "4"
        ],
        "steps": 1,
        "tokens": 2475
      },
      {
        "question": "Who was the first American to walk in space ?",
        "answer": "0",
        "ground_truth": [
          "0"
        ],
        "steps": 1,
        "tokens": 1685
      },
      {
        "question": "What are pediatricians ?",
        "answer": "3",
        "ground_truth": [
          "3"
        ],
        "steps": 1,
        "tokens": 2645
      },
      {
        "question": "What is the sales tax rate in New York ?",
        "answer": "4",
        "ground_truth": [
          "4"
        ],
        "steps": 1,
        "tokens": 2584
      },
      {
        "question": "What is the money they use in Zambia ?",
        "answer": "1",
        "ground_truth": [
          "1"
        ],
        "steps": 1,
        "tokens": 3327
      },
      {
        "question": "What is acetic acid ?",
        "answer": "3",
        "ground_truth": [
          "3"
        ],
        "steps": 1,
        "tokens": 2566
      },
      {
        "question": "When was Lyndon B. Johnson born ?",
        "answer": "4",
        "ground_truth": [
          "4"
        ],
        "steps": 1,
        "tokens": 1377
      },
      {
        "question": "In what spacecraft did U.S. astronaut Alan Shepard make his historic 1961 flight ?",
        "answer": "1",
        "ground_truth": [
          "1"
        ],
        "steps": 1,
        "tokens": 2380
      },
      {
        "question": "How cold should a refrigerator be ?",
        "answer": "4",
        "ground_truth": [
          "4"
        ],
        "steps": 1,
        "tokens": 2160
      },
      {
        "question": "What is another astronomic term for the Northern Lights ?",
        "answer": "1",
        "ground_truth": [
          "1"
        ],
        "steps": 1,
        "tokens": 2295
      },
      {
        "question": "Where is the Shawnee National Forest ?",
        "answer": "5",
        "ground_truth": [
          "5"
        ],
        "steps": 1,
        "tokens": 2912
      },
      {
        "question": "How much of an apple is water ?",
        "answer": "4",
        "ground_truth": [
          "4"
        ],
        "steps": 1,
        "tokens": 2726
      },
      {
        "question": "What is strep throat ?",
        "answer": "1",
        "ground_truth": [
          "3"
        ],
        "steps": 1,
        "tokens": 2277
      },
      {
        "question": "What is poliomyelitis ?",
        "answer": "3",
        "ground_truth": [
          "3"
        ],
        "steps": 1,
        "tokens": 2585
      },
      {
        "question": "What is the temperature at the center of the earth ?",
        "answer": "4",
        "ground_truth": [
          "4"
        ],
        "steps": 1,
        "tokens": 2940
      },
      {
        "question": "Where is the Lourve ?",
        "answer": "5",
        "ground_truth": [
          "5"
        ],
        "steps": 1,
        "tokens": 2177
      },
      {
        "question": "What is the longest bone in the human body ?",
        "answer": "1",
        "ground_truth": [
          "1"
        ],
        "steps": 1,
        "tokens": 3025
      },
      {
        "question": "What state has the least amount of rain per year ?",
        "answer": "5",
        "ground_truth": [
          "5"
        ],
        "steps": 1,
        "tokens": 1560
      },
      {
        "question": "What is neurology ?",
        "answer": "3",
        "ground_truth": [
          "3"
        ],
        "steps": 1,
        "tokens": 2503
      },
      {
        "question": "What is the statue of liberty made of ?",
        "answer": "3",
        "ground_truth": [
          "1"
        ],
        "steps": 1,
        "tokens": 2263
      },
      {
        "question": "What was W.C. Fields ' real name ?",
        "answer": "0",
        "ground_truth": [
          "0"
        ],
        "steps": 1,
        "tokens": 2242
      },
      {
        "question": "What is solar wind ?",
        "answer": "3",
        "ground_truth": [
          "3"
        ],
        "steps": 1,
        "tokens": 2624
      },
      {
        "question": "What position did Willie Davis play in baseball ?",
        "answer": "1",
        "ground_truth": [
          "0"
        ],
        "steps": 1,
        "tokens": 2476
      },
      {
        "question": "Who was the abolitionist who led the raid on Harper 's Ferry in 1859 ?",
        "answer": "0",
        "ground_truth": [
          "0"
        ],
        "steps": 1,
        "tokens": 2645
      },
      {
        "question": "Who was the first woman governor in the U.S. ?",
        "answer": "0",
        "ground_truth": [
          "0"
        ],
        "steps": 1,
        "tokens": 1513
      },
      {
        "question": "What are solar cells ?",
        "answer": "1",
        "ground_truth": [
          "3"
        ],
        "steps": 1,
        "tokens": 2302
      },
      {
        "question": "When was the telephone invented ?",
        "answer": "4",
        "ground_truth": [
          "4"
        ],
        "steps": 1,
        "tokens": 2711
      },
      {
        "question": "What is another name for vitamin B1 ?",
        "answer": "1",
        "ground_truth": [
          "1"
        ],
        "steps": 1,
        "tokens": 2420
      },
      {
        "question": "What is the major fault line near Kentucky ?",
        "answer": "1",
        "ground_truth": [
          "1"
        ],
        "steps": 1,
        "tokens": 2713
      },
      {
        "question": "Where is the Savannah River ?",
        "answer": "5",
        "ground_truth": [
          "5"
        ],
        "steps": 1,
        "tokens": 2299
      },
      {
        "question": "What city 's newspaper is called `` The Star '' ?",
        "answer": "5",
        "ground_truth": [
          "5"
        ],
        "steps": 1,
        "tokens": 3087
      },
      {
        "question": "What planet has the strongest magnetic field of all the planets ?",
        "answer": "5",
        "ground_truth": [
          "5"
        ],
        "steps": 1,
        "tokens": 1981
      },
      {
        "question": "What is severance pay ?",
        "answer": "3",
        "ground_truth": [
          "3"
        ],
        "steps": 1,
        "tokens": 2829
      },
      {
        "question": "What breed of hunting dog did the Beverly Hillbillies own ?",
        "answer": "1",
        "ground_truth": [
          "1"
        ],
        "steps": 1,
        "tokens": 2612
      },
      {
        "question": "What is the population of China ?",
        "answer": "4",
        "ground_truth": [
          "4"
        ],
        "steps": 1,
        "tokens": 1489
      },
      {
        "question": "What are semiconductors ?",
        "answer": "2",
        "ground_truth": [
          "3"
        ],
        "steps": 1,
        "tokens": 2276
      },
      {
        "question": "What body of water are the Canary Islands in ?",
        "answer": "2",
        "ground_truth": [
          "5"
        ],
        "steps": 1,
        "tokens": 1557
      },
      {
        "question": "What does the word fortnight mean ?",
        "answer": "3",
        "ground_truth": [
          "3"
        ],
        "steps": 1,
        "tokens": 2990
      },
      {
        "question": "What monastery was raided by Vikings in the late eighth century ?",
        "answer": "1",
        "ground_truth": [
          "1"
        ],
        "steps": 1,
        "tokens": 2762
      },
      {
        "question": "What did Edward Binney and Howard Smith invent in 1903 ?",
        "answer": "0",
        "ground_truth": [
          "1"
        ],
        "steps": 1,
        "tokens": 2450
      },
      {
        "question": "When was President Kennedy shot ?",
        "answer": "4",
        "ground_truth": [
          "4"
        ],
        "steps": 1,
        "tokens": 2794
      },
      {
        "question": "What is a thermometer ?",
        "answer": "3",
        "ground_truth": [
          "3"
        ],
        "steps": 1,
        "tokens": 2680
      },
      {
        "question": "What is the earth 's diameter ?",
        "answer": "4",
        "ground_truth": [
          "4"
        ],
        "steps": 1,
        "tokens": 2807
      },
      {
        "question": "What is mold ?",
        "answer": "2",
        "ground_truth": [
          "3"
        ],
        "steps": 1,
        "tokens": 2473
      },
      {
        "question": "What does `` Sitting Shiva '' mean ?",
        "answer": "2",
        "ground_truth": [
          "3"
        ],
        "steps": 1,
        "tokens": 1497
      },
      {
        "question": "What is desktop publishing ?",
        "answer": "3",
        "ground_truth": [
          "3"
        ],
        "steps": 1,
        "tokens": 2705
      },
      {
        "question": "Who discovered radium ?",
        "answer": "0",
        "ground_truth": [
          "0"
        ],
        "steps": 1,
        "tokens": 1692
      },
      {
        "question": "What is mad cow disease ?",
        "answer": "3",
        "ground_truth": [
          "3"
        ],
        "steps": 1,
        "tokens": 2686
      },
      {
        "question": "What is the location of Lake Champlain ?",
        "answer": "5",
        "ground_truth": [
          "5"
        ],
        "steps": 1,
        "tokens": 1731
      },
      {
        "question": "What is the proper name for a female walrus ?",
        "answer": "1",
        "ground_truth": [
          "1"
        ],
        "steps": 1,
        "tokens": 2883
      },
      {
        "question": "When was Rosa Parks born ?",
        "answer": "4",
        "ground_truth": [
          "4"
        ],
        "steps": 1,
        "tokens": 1534
      },
      {
        "question": "When were William Shakespeare 's twins born ?",
        "answer": "4",
        "ground_truth": [
          "4"
        ],
        "steps": 1,
        "tokens": 2216
      },
      {
        "question": "What is natural gas composed of ?",
        "answer": "1",
        "ground_truth": [
          "1"
        ],
        "steps": 1,
        "tokens": 3239
      },
      {
        "question": "How tall is the Gateway Arch in St. Louis , MO ?",
        "answer": "4",
        "ground_truth": [
          "4"
        ],
        "steps": 1,
        "tokens": 2893
      },
      {
        "question": "Who was the first governor of Alaska ?",
        "answer": "0",
        "ground_truth": [
          "0"
        ],
        "steps": 1,
        "tokens": 2375
      },
      {
        "question": "When was the first Wal-Mart store opened ?",
        "answer": "4",
        "ground_truth": [
          "4"
        ],
        "steps": 1,
        "tokens": 2644
      },
      {
        "question": "What New York City structure is also known as the Twin Towers ?",
        "answer": "1",
        "ground_truth": [
          "5"
        ],
        "steps": 1,
        "tokens": 2191
      }
    ],
    "R2": [
      {
        "question": "What is the population of Venezuela ?",
        "error": "'int' object has no attribute 'get'"
      },
      {
        "question": "What does target heart rate mean ?",
        "error": "'int' object has no attribute 'get'"
      },
      {
        "question": "What currency does Luxembourg use ?",
        "answer": "1",
        "ground_truth": [
          "1"
        ],
        "steps": 5,
        "tokens": 20029
      },
      {
        "question": "How long did Rip Van Winkle sleep ?",
        "error": "'int' object has no attribute 'get'"
      },
      {
        "question": "Material called linen is made from what plant ?",
        "error": "'int' object has no attribute 'get'"
      },
      {
        "question": "What is phenylalanine ?",
        "answer": "3",
        "ground_truth": [
          "3"
        ],
        "steps": 5,
        "tokens": 20409
      },
      {
        "question": "What is a group of turkeys called ?",
        "answer": "1",
        "ground_truth": [
          "1"
        ],
        "steps": 2,
        "tokens": 7252
      },
      {
        "question": "What are enzymes ?",
        "error": "'int' object has no attribute 'get'"
      },
      {
        "question": "Why is the sun yellow ?",
        "answer": "3",
        "ground_truth": [
          "3"
        ],
        "steps": 3,
        "tokens": 10756
      },
      {
        "question": "What state is the geographic center of the lower 48 states ?",
        "error": "'int' object has no attribute 'get'"
      },
      {
        "question": "What is foot and mouth disease ?",
        "error": "'int' object has no attribute 'get'"
      },
      {
        "question": "What is sonar ?",
        "answer": "2",
        "ground_truth": [
          "3"
        ],
        "steps": 3,
        "tokens": 9435
      },
      {
        "question": "When was Thomas Jefferson born ?",
        "answer": "4",
        "ground_truth": [
          "4"
        ],
        "steps": 5,
        "tokens": 13076
      },
      {
        "question": "What is the Ohio state bird ?",
        "answer": "1",
        "ground_truth": [
          "1"
        ],
        "steps": 3,
        "tokens": 8415
      },
      {
        "question": "What are the colors of the German flag ?",
        "answer": "1",
        "ground_truth": [
          "1"
        ],
        "steps": 4,
        "tokens": 11955
      },
      {
        "question": "Who won Ms. American in 1989 ?",
        "error": "'int' object has no attribute 'get'"
      },
      {
        "question": "Where on the body is a mortarboard worn ?",
        "answer": "5",
        "ground_truth": [
          "5"
        ],
        "steps": 4,
        "tokens": 14555
      },
      {
        "question": "What is the width of a football field ?",
        "error": "'int' object has no attribute 'get'"
      },
      {
        "question": "Who is the Prime Minister of Canada ?",
        "error": "'int' object has no attribute 'get'"
      },
      {
        "question": "What is the conversion rate between dollars and pounds ?",
        "answer": "4",
        "ground_truth": [
          "4"
        ],
        "steps": 3,
        "tokens": 8075
      },
      {
        "question": "What is fibromyalgia ?",
        "error": "'int' object has no attribute 'get'"
      },
      {
        "question": "What are the spots on dominoes called ?",
        "error": "'int' object has no attribute 'get'"
      },
      {
        "question": "What city is also known as `` The Gateway to the West '' ?",
        "answer": "5",
        "ground_truth": [
          "5"
        ],
        "steps": 2,
        "tokens": 5766
      },
      {
        "question": "Who discovered x-rays ?",
        "answer": "0",
        "ground_truth": [
          "0"
        ],
        "steps": 2,
        "tokens": 5409
      },
      {
        "question": "How much does water weigh ?",
        "answer": "4",
        "ground_truth": [
          "4"
        ],
        "steps": 2,
        "tokens": 5730
      },
      {
        "question": "Mercury , what year was it discovered ?",
        "error": "'int' object has no attribute 'get'"
      },
      {
        "question": "Where do apple snails live ?",
        "error": "'int' object has no attribute 'get'"
      },
      {
        "question": "What is the rainiest place on Earth ?",
        "error": "'int' object has no attribute 'get'"
      },
      {
        "question": "Who invented the hula hoop ?",
        "error": "'int' object has no attribute 'get'"
      },
      {
        "question": "What is the longest suspension bridge in the U.S. ?",
        "error": "'int' object has no attribute 'get'"
      },
      {
        "question": "What is plastic made of ?",
        "error": "'int' object has no attribute 'get'"
      },
      {
        "question": "How far is it from Denver to Aspen ?",
        "error": "'int' object has no attribute 'get'"
      },
      {
        "question": "What is the criterion for being legally blind ?",
        "answer": "3",
        "ground_truth": [
          "1"
        ],
        "steps": 5,
        "tokens": 20099
      },
      {
        "question": "Who invented the instant Polaroid camera ?",
        "error": "'int' object has no attribute 'get'"
      },
      {
        "question": "What is the distance in miles from the earth to the sun ?",
        "error": "'int' object has no attribute 'get'"
      },
      {
        "question": "In which state would you find the Catskill Mountains ?",
        "answer": "5",
        "ground_truth": [
          "5"
        ],
        "steps": 3,
        "tokens": 7769
      },
      {
        "question": "What is a prism ?",
        "error": "'int' object has no attribute 'get'"
      },
      {
        "question": "How fast is sound ?",
        "answer": "4",
        "ground_truth": [
          "4"
        ],
        "steps": 3,
        "tokens": 9867
      },
      {
        "question": "What does cc in engines mean ?",
        "answer": "2",
        "ground_truth": [
          "3"
        ],
        "steps": 5,
        "tokens": 20324
      },
      {
        "question": "What is an ulcer ?",
        "answer": "4",
        "ground_truth": [
          "3"
        ],
        "steps": 3,
        "tokens": 9940
      },
      {
        "question": "What is compounded interest ?",
        "answer": "0",
        "ground_truth": [
          "3"
        ],
        "steps": 5,
        "tokens": 19745
      },
      {
        "question": "What does CPR stand for ?",
        "answer": "2",
        "ground_truth": [
          "2"
        ],
        "steps": 2,
        "tokens": 6020
      },
      {
        "question": "What is hybridization ?",
        "answer": "3",
        "ground_truth": [
          "3"
        ],
        "steps": 4,
        "tokens": 16380
      },
      {
        "question": "How fast is alcohol absorbed ?",
        "answer": "4",
        "ground_truth": [
          "4"
        ],
        "steps": 3,
        "tokens": 11445
      },
      {
        "question": "Who was the first American to walk in space ?",
        "error": "'int' object has no attribute 'get'"
      },
      {
        "question": "What are pediatricians ?",
        "answer": "3",
        "ground_truth": [
          "3"
        ],
        "steps": 3,
        "tokens": 8677
      },
      {
        "question": "What is the sales tax rate in New York ?",
        "answer": "4",
        "ground_truth": [
          "4"
        ],
        "steps": 4,
        "tokens": 13517
      },
      {
        "question": "What is the money they use in Zambia ?",
        "answer": "1",
        "ground_truth": [
          "1"
        ],
        "steps": 5,
        "tokens": 18520
      },
      {
        "question": "What is acetic acid ?",
        "answer": "1",
        "ground_truth": [
          "3"
        ],
        "steps": 2,
        "tokens": 6073
      },
      {
        "question": "When was Lyndon B. Johnson born ?",
        "answer": "4",
        "ground_truth": [
          "4"
        ],
        "steps": 5,
        "tokens": 14875
      },
      {
        "question": "In what spacecraft did U.S. astronaut Alan Shepard make his historic 1961 flight ?",
        "answer": "1",
        "ground_truth": [
          "1"
        ],
        "steps": 3,
        "tokens": 11944
      },
      {
        "question": "How cold should a refrigerator be ?",
        "answer": "4",
        "ground_truth": [
          "4"
        ],
        "steps": 3,
        "tokens": 9254
      },
      {
        "question": "What is another astronomic term for the Northern Lights ?",
        "answer": "1",
        "ground_truth": [
          "1"
        ],
        "steps": 5,
        "tokens": 17753
      },
      {
        "question": "Where is the Shawnee National Forest ?",
        "error": "'int' object has no attribute 'get'"
      },
      {
        "question": "How much of an apple is water ?",
        "error": "'int' object has no attribute 'get'"
      },
      {
        "question": "What is strep throat ?",
        "error": "'int' object has no attribute 'get'"
      },
      {
        "question": "What is poliomyelitis ?",
        "answer": "4",
        "ground_truth": [
          "3"
        ],
        "steps": 2,
        "tokens": 5525
      },
      {
        "question": "What is the temperature at the center of the earth ?",
        "answer": "4",
        "ground_truth": [
          "4"
        ],
        "steps": 5,
        "tokens": 17079
      },
      {
        "question": "Where is the Lourve ?",
        "answer": "5",
        "ground_truth": [
          "5"
        ],
        "steps": 2,
        "tokens": 4913
      },
      {
        "question": "What is the longest bone in the human body ?",
        "answer": "1",
        "ground_truth": [
          "1"
        ],
        "steps": 3,
        "tokens": 9072
      },
      {
        "question": "What state has the least amount of rain per year ?",
        "error": "'int' object has no attribute 'get'"
      },
      {
        "question": "What is neurology ?",
        "error": "'int' object has no attribute 'get'"
      },
      {
        "question": "What is the statue of liberty made of ?",
        "error": "'int' object has no attribute 'get'"
      },
      {
        "question": "What was W.C. Fields ' real name ?",
        "answer": "1",
        "ground_truth": [
          "0"
        ],
        "steps": 5,
        "tokens": 15928
      },
      {
        "question": "What is solar wind ?",
        "error": "'int' object has no attribute 'get'"
      },
      {
        "question": "What position did Willie Davis play in baseball ?",
        "error": "'int' object has no attribute 'get'"
      },
      {
        "question": "Who was the abolitionist who led the raid on Harper 's Ferry in 1859 ?",
        "error": "'int' object has no attribute 'get'"
      },
      {
        "question": "Who was the first woman governor in the U.S. ?",
        "error": "Error code: 429 - {'error': {'code': 'RateLimitExceeded.EndpointTPMExceeded', 'message': 'The Tokens Per Minute (TPM) limit of the associated endpoint for your account has been exceeded, please retry later or contact with administrator if not work afterwards. Request id: 0217703762843777fbfe5bd10ef69e0c508f864fad73fe07f5c2d', 'param': '', 'type': 'TooManyRequests'}}"
      },
      {
        "question": "What are solar cells ?",
        "answer": "3",
        "ground_truth": [
          "3"
        ],
        "steps": 2,
        "tokens": 6668
      },
      {
        "question": "When was the telephone invented ?",
        "answer": "4",
        "ground_truth": [
          "4"
        ],
        "steps": 2,
        "tokens": 5630
      },
      {
        "question": "What is another name for vitamin B1 ?",
        "error": "'int' object has no attribute 'get'"
      },
      {
        "question": "What is the major fault line near Kentucky ?",
        "answer": "3",
        "ground_truth": [
          "1"
        ],
        "steps": 3,
        "tokens": 10764
      },
      {
        "question": "Where is the Savannah River ?",
        "error": "'int' object has no attribute 'get'"
      },
      {
        "question": "What city 's newspaper is called `` The Star '' ?",
        "answer": "5",
        "ground_truth": [
          "5"
        ],
        "steps": 5,
        "tokens": 18211
      },
      {
        "question": "What planet has the strongest magnetic field of all the planets ?",
        "error": "'int' object has no attribute 'get'"
      },
      {
        "question": "What is severance pay ?",
        "answer": "2",
        "ground_truth": [
          "3"
        ],
        "steps": 2,
        "tokens": 6142
      },
      {
        "question": "What breed of hunting dog did the Beverly Hillbillies own ?",
        "error": "'int' object has no attribute 'get'"
      },
      {
        "question": "What is the population of China ?",
        "answer": "4",
        "ground_truth": [
          "4"
        ],
        "steps": 5,
        "tokens": 17162
      },
      {
        "question": "What are semiconductors ?",
        "error": "'int' object has no attribute 'get'"
      },
      {
        "question": "What body of water are the Canary Islands in ?",
        "error": "'int' object has no attribute 'get'"
      },
      {
        "question": "What does the word fortnight mean ?",
        "answer": "3",
        "ground_truth": [
          "3"
        ],
        "steps": 4,
        "tokens": 12953
      },
      {
        "question": "What monastery was raided by Vikings in the late eighth century ?",
        "error": "'int' object has no attribute 'get'"
      },
      {
        "question": "What did Edward Binney and Howard Smith invent in 1903 ?",
        "error": "'int' object has no attribute 'get'"
      },
      {
        "question": "When was President Kennedy shot ?",
        "error": "'int' object has no attribute 'get'"
      },
      {
        "question": "What is a thermometer ?",
        "error": "Request timed out."
      },
      {
        "question": "What is the earth 's diameter ?",
        "error": "Request timed out."
      },
      {
        "question": "What is mold ?",
        "error": "Request timed out."
      },
      {
        "question": "What does `` Sitting Shiva '' mean ?",
        "answer": "2",
        "ground_truth": [
          "3"
        ],
        "steps": 4,
        "tokens": 15801
      },
      {
        "question": "What is desktop publishing ?",
        "answer": "3",
        "ground_truth": [
          "3"
        ],
        "steps": 2,
        "tokens": 6194
      },
      {
        "question": "Who discovered radium ?",
        "error": "'int' object has no attribute 'get'"
      },
      {
        "question": "What is mad cow disease ?",
        "answer": "3",
        "ground_truth": [
          "3"
        ],
        "steps": 2,
        "tokens": 6663
      },
      {
        "question": "What is the location of Lake Champlain ?",
        "error": "'int' object has no attribute 'get'"
      },
      {
        "question": "What is the proper name for a female walrus ?",
        "answer": "1",
        "ground_truth": [
          "1"
        ],
        "steps": 3,
        "tokens": 7860
      },
      {
        "question": "When was Rosa Parks born ?",
        "answer": "4",
        "ground_truth": [
          "4"
        ],
        "steps": 5,
        "tokens": 14522
      },
      {
        "question": "When were William Shakespeare 's twins born ?",
        "error": "'int' object has no attribute 'get'"
      },
      {
        "question": "What is natural gas composed of ?",
        "error": "'int' object has no attribute 'get'"
      },
      {
        "question": "How tall is the Gateway Arch in St. Louis , MO ?",
        "answer": "4",
        "ground_truth": [
          "4"
        ],
        "steps": 2,
        "tokens": 6128
      },
      {
        "question": "Who was the first governor of Alaska ?",
        "error": "'int' object has no attribute 'get'"
      },
      {
        "question": "When was the first Wal-Mart store opened ?",
        "error": "'int' object has no attribute 'get'"
      },
      {
        "question": "What New York City structure is also known as the Twin Towers ?",
        "answer": "1",
        "ground_truth": [
          "5"
        ],
        "steps": 5,
        "tokens": 20098
      }
    ],
    "R3": [
      {
        "question": "What is the population of Venezuela ?",
        "answer": "4",
        "ground_truth": [
          "4"
        ],
        "steps": 2,
        "tokens": 9291
      },
      {
        "question": "What does target heart rate mean ?",
        "answer": "3",
        "ground_truth": [
          "3"
        ],
        "steps": 3,
        "tokens": 15920
      },
      {
        "question": "What currency does Luxembourg use ?",
        "answer": "1",
        "ground_truth": [
          "1"
        ],
        "steps": 2,
        "tokens": 12601
      },
      {
        "question": "How long did Rip Van Winkle sleep ?",
        "answer": "4",
        "ground_truth": [
          "4"
        ],
        "steps": 3,
        "tokens": 17767
      },
      {
        "question": "Material called linen is made from what plant ?",
        "answer": "1",
        "ground_truth": [
          "1"
        ],
        "steps": 2,
        "tokens": 12847
      },
      {
        "question": "What is phenylalanine ?",
        "error": "'int' object has no attribute 'get'"
      },
      {
        "question": "What is a group of turkeys called ?",
        "answer": "1",
        "ground_truth": [
          "1"
        ],
        "steps": 2,
        "tokens": 11975
      },
      {
        "question": "What are enzymes ?",
        "answer": "3",
        "ground_truth": [
          "3"
        ],
        "steps": 4,
        "tokens": 26758
      },
      {
        "question": "Why is the sun yellow ?",
        "answer": "3",
        "ground_truth": [
          "3"
        ],
        "steps": 7,
        "tokens": 60572
      },
      {
        "question": "What state is the geographic center of the lower 48 states ?",
        "answer": "5",
        "ground_truth": [
          "5"
        ],
        "steps": 2,
        "tokens": 9365
      },
      {
        "question": "What is foot and mouth disease ?",
        "answer": "3",
        "ground_truth": [
          "1"
        ],
        "steps": 2,
        "tokens": 11375
      },
      {
        "question": "What is sonar ?",
        "answer": "2",
        "ground_truth": [
          "3"
        ],
        "steps": 2,
        "tokens": 13726
      },
      {
        "question": "When was Thomas Jefferson born ?",
        "error": "'int' object has no attribute 'get'"
      },
      {
        "question": "What is the Ohio state bird ?",
        "answer": "1",
        "ground_truth": [
          "1"
        ],
        "steps": 2,
        "tokens": 9705
      },
      {
        "question": "What are the colors of the German flag ?",
        "answer": "1",
        "ground_truth": [
          "1"
        ],
        "steps": 2,
        "tokens": 9126
      },
      {
        "question": "Who won Ms. American in 1989 ?",
        "answer": "0",
        "ground_truth": [
          "0"
        ],
        "steps": 4,
        "tokens": 24329
      },
      {
        "question": "Where on the body is a mortarboard worn ?",
        "answer": "5",
        "ground_truth": [
          "5"
        ],
        "steps": 2,
        "tokens": 12677
      },
      {
        "question": "What is the width of a football field ?",
        "answer": "4",
        "ground_truth": [
          "4"
        ],
        "steps": 2,
        "tokens": 11391
      },
      {
        "question": "Who is the Prime Minister of Canada ?",
        "answer": "0",
        "ground_truth": [
          "0"
        ],
        "steps": 3,
        "tokens": 18359
      },
      {
        "question": "What is the conversion rate between dollars and pounds ?",
        "answer": "4",
        "ground_truth": [
          "4"
        ],
        "steps": 2,
        "tokens": 12127
      },
      {
        "question": "What is fibromyalgia ?",
        "answer": "1",
        "ground_truth": [
          "3"
        ],
        "steps": 2,
        "tokens": 15203
      },
      {
        "question": "What are the spots on dominoes called ?",
        "answer": "3",
        "ground_truth": [
          "1"
        ],
        "steps": 2,
        "tokens": 11614
      },
      {
        "question": "What city is also known as `` The Gateway to the West '' ?",
        "answer": "5",
        "ground_truth": [
          "5"
        ],
        "steps": 2,
        "tokens": 11562
      },
      {
        "question": "Who discovered x-rays ?",
        "answer": "0",
        "ground_truth": [
          "0"
        ],
        "steps": 2,
        "tokens": 9873
      },
      {
        "question": "How much does water weigh ?",
        "answer": "4",
        "ground_truth": [
          "4"
        ],
        "steps": 2,
        "tokens": 9686
      },
      {
        "question": "Mercury , what year was it discovered ?",
        "answer": "4",
        "ground_truth": [
          "4"
        ],
        "steps": 5,
        "tokens": 35774
      },
      {
        "question": "Where do apple snails live ?",
        "answer": "5",
        "ground_truth": [
          "5"
        ],
        "steps": 2,
        "tokens": 11469
      },
      {
        "question": "What is the rainiest place on Earth ?",
        "answer": "5",
        "ground_truth": [
          "5"
        ],
        "steps": 2,
        "tokens": 13116
      },
      {
        "question": "Who invented the hula hoop ?",
        "error": "'int' object has no attribute 'get'"
      },
      {
        "question": "What is the longest suspension bridge in the U.S. ?",
        "answer": "5",
        "ground_truth": [
          "5"
        ],
        "steps": 2,
        "tokens": 11891
      },
      {
        "question": "What is plastic made of ?",
        "answer": "1",
        "ground_truth": [
          "1"
        ],
        "steps": 3,
        "tokens": 17882
      },
      {
        "question": "How far is it from Denver to Aspen ?",
        "answer": "4",
        "ground_truth": [
          "4"
        ],
        "steps": 2,
        "tokens": 11485
      },
      {
        "question": "What is the criterion for being legally blind ?",
        "answer": "{3}",
        "ground_truth": [
          "1"
        ],
        "steps": 6,
        "tokens": 120093,
        "latency_s": 187.57,
        "replan": 1
      },
      {
        "question": "Who invented the instant Polaroid camera ?",
        "answer": "{0}",
        "ground_truth": [
          "0"
        ],
        "steps": 1,
        "tokens": 8355,
        "latency_s": 44.45,
        "replan": 0
      },
      {
        "question": "What is the distance in miles from the earth to the sun ?",
        "answer": "{4}",
        "ground_truth": [
          "4"
        ],
        "steps": 2,
        "tokens": 21012,
        "latency_s": 104.43,
        "replan": 0
      },
      {
        "question": "In which state would you find the Catskill Mountains ?",
        "answer": "{5}",
        "ground_truth": [
          "5"
        ],
        "steps": 2,
        "tokens": 20343,
        "latency_s": 67.45,
        "replan": 0
      },
      {
        "question": "What is a prism ?",
        "answer": "{1}",
        "ground_truth": [
          "3"
        ],
        "steps": 3,
        "tokens": 41046,
        "latency_s": 188.81,
        "replan": 0
      },
      {
        "question": "How fast is sound ?",
        "answer": "{4}",
        "ground_truth": [
          "4"
        ],
        "steps": 1,
        "tokens": 8331,
        "latency_s": 61.84,
        "replan": 0
      },
      {
        "question": "What does cc in engines mean ?",
        "answer": "{2}",
        "ground_truth": [
          "3"
        ],
        "steps": 2,
        "tokens": 23276,
        "latency_s": 138.06,
        "replan": 0
      },
      {
        "question": "What is an ulcer ?",
        "answer": "{3}",
        "ground_truth": [
          "3"
        ],
        "steps": 1,
        "tokens": 8924,
        "latency_s": 78.75,
        "replan": 0
      },
      {
        "question": "What is compounded interest ?",
        "answer": "{3}",
        "ground_truth": [
          "3"
        ],
        "steps": 2,
        "tokens": 21909,
        "latency_s": 127.1,
        "replan": 0
      },
      {
        "question": "What does CPR stand for ?",
        "answer": "{2}",
        "ground_truth": [
          "2"
        ],
        "steps": 1,
        "tokens": 8299,
        "latency_s": 45.55,
        "replan": 0
      },
      {
        "question": "What is hybridization ?",
        "answer": "{3}",
        "ground_truth": [
          "3"
        ],
        "steps": 2,
        "tokens": 22313,
        "latency_s": 154.8,
        "replan": 0
      },
      {
        "question": "How fast is alcohol absorbed ?",
        "answer": "{4}",
        "ground_truth": [
          "4"
        ],
        "steps": 1,
        "tokens": 8842,
        "latency_s": 66.64,
        "replan": 0
      },
      {
        "question": "Who was the first American to walk in space ?",
        "answer": "{0}",
        "ground_truth": [
          "0"
        ],
        "steps": 2,
        "tokens": 22791,
        "latency_s": 116.42,
        "replan": 0
      },
      {
        "question": "What are pediatricians ?",
        "answer": "{3}",
        "ground_truth": [
          "3"
        ],
        "steps": 1,
        "tokens": 9381,
        "latency_s": 86.57,
        "replan": 0
      },
      {
        "question": "What is the sales tax rate in New York ?",
        "answer": "{4}",
        "ground_truth": [
          "4"
        ],
        "steps": 1,
        "tokens": 9687,
        "latency_s": 92.77,
        "replan": 0
      },
      {
        "question": "What is the money they use in Zambia ?",
        "answer": "{1}",
        "ground_truth": [
          "1"
        ],
        "steps": 1,
        "tokens": 9281,
        "latency_s": 82.17,
        "replan": 0
      },
      {
        "question": "What is acetic acid ?",
        "answer": "{3}",
        "ground_truth": [
          "3"
        ],
        "steps": 1,
        "tokens": 10691,
        "latency_s": 118.7,
        "replan": 0
      },
      {
        "question": "When was Lyndon B. Johnson born ?",
        "answer": "{4}",
        "ground_truth": [
          "4"
        ],
        "steps": 1,
        "tokens": 8369,
        "latency_s": 63.59,
        "replan": 0
      },
      {
        "question": "In what spacecraft did U.S. astronaut Alan Shepard make his historic 1961 flight ?",
        "answer": "{1}",
        "ground_truth": [
          "1"
        ],
        "steps": 2,
        "tokens": 21824,
        "latency_s": 108.56,
        "replan": 0
      },
      {
        "question": "How cold should a refrigerator be ?",
        "answer": "{4}",
        "ground_truth": [
          "4"
        ],
        "steps": 1,
        "tokens": 10644,
        "latency_s": 119.21,
        "replan": 0
      },
      {
        "question": "What is another astronomic term for the Northern Lights ?",
        "answer": "{1}",
        "ground_truth": [
          "1"
        ],
        "steps": 2,
        "tokens": 21488,
        "latency_s": 95.22,
        "replan": 0
      },
      {
        "question": "Where is the Shawnee National Forest ?",
        "answer": "{5}",
        "ground_truth": [
          "5"
        ],
        "steps": 1,
        "tokens": 8608,
        "latency_s": 62.71,
        "replan": 0
      },
      {
        "question": "How much of an apple is water ?",
        "answer": "{4}",
        "ground_truth": [
          "4"
        ],
        "steps": 1,
        "tokens": 8636,
        "latency_s": 62.23,
        "replan": 0
      },
      {
        "question": "What is strep throat ?",
        "answer": "{3}",
        "ground_truth": [
          "3"
        ],
        "steps": 1,
        "tokens": 9372,
        "latency_s": 92.98,
        "replan": 0
      },
      {
        "question": "What is poliomyelitis ?",
        "answer": "{1}",
        "ground_truth": [
          "3"
        ],
        "steps": 1,
        "tokens": 9388,
        "latency_s": 76.49,
        "replan": 0
      },
      {
        "question": "What is the temperature at the center of the earth ?",
        "answer": "{4}",
        "ground_truth": [
          "4"
        ],
        "steps": 1,
        "tokens": 8537,
        "latency_s": 63.94,
        "replan": 0
      },
      {
        "question": "Where is the Lourve ?",
        "answer": "{5}",
        "ground_truth": [
          "5"
        ],
        "steps": 1,
        "tokens": 8051,
        "latency_s": 46.1,
        "replan": 0
      },
      {
        "question": "What is the longest bone in the human body ?",
        "answer": "{1}",
        "ground_truth": [
          "1"
        ],
        "steps": 3,
        "tokens": 39273,
        "latency_s": 143.6,
        "replan": 0
      },
      {
        "question": "What state has the least amount of rain per year ?",
        "answer": "{5}",
        "ground_truth": [
          "5"
        ],
        "steps": 2,
        "tokens": 21290,
        "latency_s": 83.72,
        "replan": 0
      },
      {
        "question": "What is neurology ?",
        "answer": "3",
        "ground_truth": [
          "3"
        ],
        "steps": 1,
        "tokens": 9204,
        "latency_s": 86.73,
        "replan": 0
      },
      {
        "question": "What is the statue of liberty made of ?",
        "answer": "{1}",
        "ground_truth": [
          "1"
        ],
        "steps": 2,
        "tokens": 21670,
        "latency_s": 108.11,
        "replan": 0
      },
      {
        "question": "What was W.C. Fields ' real name ?",
        "answer": "{0}",
        "ground_truth": [
          "0"
        ],
        "steps": 1,
        "tokens": 8722,
        "latency_s": 136.76,
        "replan": 0
      },
      {
        "question": "What is solar wind ?",
        "answer": "{3}",
        "ground_truth": [
          "3"
        ],
        "steps": 2,
        "tokens": 20830,
        "latency_s": 112.22,
        "replan": 0
      },
      {
        "question": "What position did Willie Davis play in baseball ?",
        "answer": "{0}",
        "ground_truth": [
          "0"
        ],
        "steps": 2,
        "tokens": 20927,
        "latency_s": 112.15,
        "replan": 0
      },
      {
        "question": "Who was the abolitionist who led the raid on Harper 's Ferry in 1859 ?",
        "answer": "{0}",
        "ground_truth": [
          "0"
        ],
        "steps": 2,
        "tokens": 21586,
        "latency_s": 99.67,
        "replan": 0
      },
      {
        "question": "Who was the first woman governor in the U.S. ?",
        "answer": "{0}",
        "ground_truth": [
          "0"
        ],
        "steps": 2,
        "tokens": 22517,
        "latency_s": 141.57,
        "replan": 0
      },
      {
        "question": "What are solar cells ?",
        "answer": "{3}",
        "ground_truth": [
          "3"
        ],
        "steps": 1,
        "tokens": 12297,
        "latency_s": 201.86,
        "replan": 0
      },
      {
        "question": "When was the telephone invented ?",
        "answer": "{4}",
        "ground_truth": [
          "4"
        ],
        "steps": 2,
        "tokens": 20507,
        "latency_s": 122.02,
        "replan": 0
      },
      {
        "question": "What is another name for vitamin B1 ?",
        "answer": "{1}",
        "ground_truth": [
          "1"
        ],
        "steps": 1,
        "tokens": 8526,
        "latency_s": 72.32,
        "replan": 0
      },
      {
        "question": "What is the major fault line near Kentucky ?",
        "answer": "{1}",
        "ground_truth": [
          "1"
        ],
        "steps": 2,
        "tokens": 22619,
        "latency_s": 130.47,
        "replan": 0
      },
      {
        "question": "Where is the Savannah River ?",
        "answer": "{5}",
        "ground_truth": [
          "5"
        ],
        "steps": 1,
        "tokens": 8169,
        "latency_s": 47.27,
        "replan": 0
      },
      {
        "question": "What city 's newspaper is called `` The Star '' ?",
        "answer": "{5}",
        "ground_truth": [
          "5"
        ],
        "steps": 2,
        "tokens": 20728,
        "latency_s": 90.94,
        "replan": 0
      },
      {
        "question": "What planet has the strongest magnetic field of all the planets ?",
        "answer": "{5}",
        "ground_truth": [
          "5"
        ],
        "steps": 2,
        "tokens": 19939,
        "latency_s": 60.89,
        "replan": 0
      },
      {
        "question": "What is severance pay ?",
        "answer": "{3}",
        "ground_truth": [
          "3"
        ],
        "steps": 2,
        "tokens": 23384,
        "latency_s": 197.24,
        "replan": 0
      },
      {
        "question": "What breed of hunting dog did the Beverly Hillbillies own ?",
        "answer": "{1}",
        "ground_truth": [
          "1"
        ],
        "steps": 1,
        "tokens": 10784,
        "latency_s": 121.87,
        "replan": 0
      },
      {
        "question": "What is the population of China ?",
        "answer": "{4}",
        "ground_truth": [
          "4"
        ],
        "steps": 1,
        "tokens": 8154,
        "latency_s": 44.91,
        "replan": 0
      },
      {
        "question": "What are semiconductors ?",
        "answer": "{3}",
        "ground_truth": [
          "3"
        ],
        "steps": 1,
        "tokens": 10837,
        "latency_s": 134.39,
        "replan": 0
      },
      {
        "question": "What body of water are the Canary Islands in ?",
        "error": "Connection error."
      },
      {
        "question": "What does the word fortnight mean ?",
        "answer": "3",
        "ground_truth": [
          "3"
        ],
        "steps": 2,
        "tokens": 21824,
        "latency_s": 201.22,
        "replan": 0
      },
      {
        "question": "What monastery was raided by Vikings in the late eighth century ?",
        "answer": "{5}",
        "ground_truth": [
          "1"
        ],
        "steps": 3,
        "tokens": 38688,
        "latency_s": 125.01,
        "replan": 0
      },
      {
        "question": "What did Edward Binney and Howard Smith invent in 1903 ?",
        "answer": "{1}",
        "ground_truth": [
          "1"
        ],
        "steps": 2,
        "tokens": 22464,
        "latency_s": 136.64,
        "replan": 0
      },
      {
        "question": "When was President Kennedy shot ?",
        "answer": "{4}",
        "ground_truth": [
          "4"
        ],
        "steps": 2,
        "tokens": 21094,
        "latency_s": 115.85,
        "replan": 0
      },
      {
        "question": "What is a thermometer ?",
        "answer": "{1}",
        "ground_truth": [
          "3"
        ],
        "steps": 1,
        "tokens": 9992,
        "latency_s": 109.93,
        "replan": 0
      },
      {
        "question": "What is the earth 's diameter ?",
        "answer": "{4}",
        "ground_truth": [
          "4"
        ],
        "steps": 1,
        "tokens": 8865,
        "latency_s": 64.27,
        "replan": 0
      },
      {
        "question": "What is mold ?",
        "answer": "{3}",
        "ground_truth": [
          "3"
        ],
        "steps": 2,
        "tokens": 22423,
        "latency_s": 138.93,
        "replan": 0
      },
      {
        "question": "What does `` Sitting Shiva '' mean ?",
        "answer": "{1}",
        "ground_truth": [
          "3"
        ],
        "steps": 2,
        "tokens": 21465,
        "latency_s": 116.84,
        "replan": 0
      },
      {
        "question": "What is desktop publishing ?",
        "answer": "{2}",
        "ground_truth": [
          "3"
        ],
        "steps": 1,
        "tokens": 9715,
        "latency_s": 102.32,
        "replan": 0
      },
      {
        "question": "Who discovered radium ?",
        "answer": "{0}",
        "ground_truth": [
          "0"
        ],
        "steps": 1,
        "tokens": 8204,
        "latency_s": 59.28,
        "replan": 0
      },
      {
        "question": "What is mad cow disease ?",
        "answer": "{2}",
        "ground_truth": [
          "3"
        ],
        "steps": 1,
        "tokens": 8779,
        "latency_s": 80.6,
        "replan": 0
      },
      {
        "question": "What is the location of Lake Champlain ?",
        "answer": "{5}",
        "ground_truth": [
          "5"
        ],
        "steps": 2,
        "tokens": 20643,
        "latency_s": 70.77,
        "replan": 0
      },
      {
        "question": "What is the proper name for a female walrus ?",
        "answer": "{1}",
        "ground_truth": [
          "1"
        ],
        "steps": 2,
        "tokens": 19613,
        "latency_s": 49.68,
        "replan": 0
      },
      {
        "question": "When was Rosa Parks born ?",
        "answer": "{4}",
        "ground_truth": [
          "4"
        ],
        "steps": 1,
        "tokens": 7796,
        "latency_s": 50.62,
        "replan": 0
      },
      {
        "question": "When were William Shakespeare 's twins born ?",
        "answer": "{4}",
        "ground_truth": [
          "4"
        ],
        "steps": 2,
        "tokens": 19443,
        "latency_s": 71.18,
        "replan": 0
      },
      {
        "question": "What is natural gas composed of ?",
        "error": "'int' object has no attribute 'get'"
      },
      {
        "question": "How tall is the Gateway Arch in St. Louis , MO ?",
        "answer": "{4}",
        "ground_truth": [
          "4"
        ],
        "steps": 1,
        "tokens": 8987,
        "latency_s": 66.52,
        "replan": 0
      },
      {
        "question": "Who was the first governor of Alaska ?",
        "answer": "{5}",
        "ground_truth": [
          "0"
        ],
        "steps": 1,
        "tokens": 10183,
        "latency_s": 100.44,
        "replan": 0
      },
      {
        "question": "When was the first Wal-Mart store opened ?",
        "answer": "{4}",
        "ground_truth": [
          "4"
        ],
        "steps": 1,
        "tokens": 8749,
        "latency_s": 62.26,
        "replan": 0
      },
      {
        "question": "What New York City structure is also known as the Twin Towers ?",
        "answer": "{5}",
        "ground_truth": [
          "5"
        ],
        "steps": 2,
        "tokens": 21636,
        "latency_s": 85.48,
        "replan": 0
      }
    ]
  }
}